xvi_mcp/__init__.py
xvi_mcp/server.py
xvi_mcp-0.1.3.dist-info/METADATA
xvi_mcp-0.1.3.dist-info/WHEEL
xvi_mcp-0.1.3.dist-info/entry_points.txt
xvi_mcp-0.1.3.dist-info/RECORD
